README.rst
setup.cfg
setup.py
afkmc2/__init__.py
afkmc2/afkmc2.py
afkmc2/demo.py
afkmc2.egg-info/PKG-INFO
afkmc2.egg-info/SOURCES.txt
afkmc2.egg-info/dependency_links.txt
afkmc2.egg-info/requires.txt
afkmc2.egg-info/top_level.txt