Metadata-Version: 1.1
Name: afkmc2
Version: 0.1
Summary: Assumption Free and Efficient K-Means Seeding
Home-page: http://afkmc2.readthedocs.io/en/latest/index.html
Author: Adrian Goedeckemeyer
Author-email: adrian+pypi@minerva.kgi.edu
License: UNKNOWN
Download-URL: https://github.com/adriangoe/afkmc2/archive/0.1.tar.gz
Keywords: kmeans,seeding,sklearn,numpy
Platform: UNKNOWN
